tdfmt/__init__.py
tdfmt/tdfmt.py
tdfmt-0.0.3.dist-info/LICENSE
tdfmt-0.0.3.dist-info/METADATA
tdfmt-0.0.3.dist-info/WHEEL
tdfmt-0.0.3.dist-info/top_level.txt
tdfmt-0.0.3.dist-info/RECORD
