Metadata-Version: 2.1
Name: tdfmt
Version: 0.0.3
Summary: tdfmt is a concise timedelta formatter
Home-page: https://github.com/bbriano/tdfmt
Author: Briano Goestiawan
Author-email: b@briano.io
Classifier: Programming Language :: Python :: 3
Classifier: Operating System :: OS Independent
Classifier: License :: OSI Approved :: ISC License (ISCL)
Requires-Python: >=3
License-File: LICENSE
